<?xml version="1.0" encoding="UTF-8"?>
<queue>
   <metadata>
      <row>
         <version>12.3.4</version>
      </row>
   </metadata>
   <general_attributes>
      <row>
         <minimum_ae_version>11.2</minimum_ae_version>
         <child_flags>00000000000000000000000000000000</child_flags>
         <last_runtimes>AAAAAAAAAAAAAAAAAAAAAAAAAAAAAAAA</last_runtimes>
         <name>QUEUE.RIS</name>
         <type>QUEUE</type>
         <priority>200</priority>
         <versioning_id>503400607</versioning_id>
      </row>
   </general_attributes>
   <queue_attributes>
      <row>
         <temp_max_slots>-1</temp_max_slots>
         <temp_priority>200</temp_priority>
         <max_slots>-1</max_slots>
      </row>
   </queue_attributes>
</queue>
